django_mermaid/__init__.py
django_mermaid/apps.py
django_mermaid/static/mermaid/9.4.3/mermaid.js
django_mermaid/templatetags/__init__.py
django_mermaid/templatetags/mermaid.py
django_mermaid-0.1.0.dist-info/LICENSE
django_mermaid-0.1.0.dist-info/METADATA
django_mermaid-0.1.0.dist-info/WHEEL
django_mermaid-0.1.0.dist-info/top_level.txt
django_mermaid-0.1.0.dist-info/RECORD
